pandas_light/__init__.py
pandas_light/column.py
pandas_light/filter.py
pandas_light/groupby.py
pandas_light/index.py
pandas_light/insert.py
pandas_light/mapping.py
pandas_light/null.py
pandas_light/reshape.py
pandas_light/tool.py
pandas_light/util.py
pandas_light-1.0.2.dist-info/LICENSE
pandas_light-1.0.2.dist-info/METADATA
pandas_light-1.0.2.dist-info/WHEEL
pandas_light-1.0.2.dist-info/top_level.txt
pandas_light-1.0.2.dist-info/RECORD
