Metadata-Version: 2.1
Name: pandas-light
Version: 1.0.2
Summary: Some pandas extensions.
Home-page: https://github.com
Author: d_mok
Author-email: unknown@gmail.com
License: MIT
Platform: UNKNOWN
Classifier: Programming Language :: Python :: 3
Classifier: License :: OSI Approved :: MIT License
Classifier: Operating System :: OS Independent
Requires-Dist: pandas
Requires-Dist: pandas-flavor
